odoo/addons/l10n_es_extra_data/README.rst
odoo/addons/l10n_es_extra_data/__init__.py
odoo/addons/l10n_es_extra_data/__manifest__.py
odoo/addons/l10n_es_extra_data/data/account_data.xml
odoo/addons/l10n_es_extra_data/data/account_fiscal_position_template_data.xml
odoo/addons/l10n_es_extra_data/data/account_tax_data.xml
odoo/addons/l10n_es_extra_data/i18n/l10n_es_extra_data.pot
odoo/addons/l10n_es_extra_data/readme/CONTRIBUTORS.rst
odoo/addons/l10n_es_extra_data/readme/DESCRIPTION.rst
odoo/addons/l10n_es_extra_data/readme/HISTORY.rst
odoo/addons/l10n_es_extra_data/readme/USAGE.rst
odoo/addons/l10n_es_extra_data/static/description/icon.png
odoo/addons/l10n_es_extra_data/static/description/index.html
odoo13_addon_l10n_es_extra_data-13.0.1.0.1.dev2.dist-info/METADATA
odoo13_addon_l10n_es_extra_data-13.0.1.0.1.dev2.dist-info/WHEEL
odoo13_addon_l10n_es_extra_data-13.0.1.0.1.dev2.dist-info/top_level.txt
odoo13_addon_l10n_es_extra_data-13.0.1.0.1.dev2.dist-info/RECORD
