Metadata-Version: 2.1
Name: odoo13-addon-l10n_es_extra_data
Version: 13.0.1.0.1.dev2
Summary: Datos extra de la localización española
Home-page: https://github.com/OCA/l10n-spain
Author: Acysos (www.acysos.com), Odoo Community Association (OCA)
Author-email: support@odoo-community.org
License: AGPL-3
Classifier: Programming Language :: Python
Classifier: Framework :: Odoo
Classifier: Framework :: Odoo :: 13.0
Classifier: License :: OSI Approved :: GNU Affero General Public License v3
Requires-Python: >=3.5
Requires-Dist: odoo<13.1dev,>=13.0a
